setup.py
match3d/__init__.py
match3d/api_operations.py
match3d/blenderbase.py
match3d/generate_images_for_humans.py
match3d/image_match_generator.py
match3d/three_d_match.py
match3d.egg-info/PKG-INFO
match3d.egg-info/SOURCES.txt
match3d.egg-info/dependency_links.txt
match3d.egg-info/requires.txt
match3d.egg-info/top_level.txt
match3d.egg-info/zip-safe