Metadata-Version: 1.1
Name: match3d
Version: 0.0.1
Summary: match3d allows you to store and search 3D models (STL files)for similar designs.
Home-page: https://github.com/ascribe/3dmatch/
Author: Ryan Henderson
Author-email: ryan@ascribe.io
License: Apache License 2.0
Platform: UNKNOWN
Classifier: Development Status :: 3 - Alpha
Classifier: Intended Audience :: Developers
Classifier: Topic :: Database
Classifier: Topic :: Database :: Database Engines/Servers
Classifier: Topic :: Software Development
Classifier: Natural Language :: English
Classifier: License :: OSI Approved :: Apache Software License
Classifier: Programming Language :: Python :: 2
Classifier: Programming Language :: Python :: 2.7
Classifier: Operating System :: MacOS :: MacOS X
Classifier: Operating System :: POSIX :: Linux
Classifier: Topic :: Multimedia :: Graphics
